rajeshPackage/__init__.py
rajeshPackage/calculations.py
rajeshPackage-0.0.1.dist-info/METADATA
rajeshPackage-0.0.1.dist-info/WHEEL
rajeshPackage-0.0.1.dist-info/top_level.txt
rajeshPackage-0.0.1.dist-info/RECORD
