Metadata-Version: 2.1
Name: rajeshPackage
Version: 0.0.1
Summary: Package for simple calculations
Author: Rajesh Nagireddy
Author-email: rajeshnagireddy90@gmail.com
